yala/__init__.py
yala/base.py
yala/config.py
yala/linters.py
yala/logging.ini
yala/main.py
yala/setup.cfg
yala-3.2.0.dist-info/LICENSE
yala-3.2.0.dist-info/METADATA
yala-3.2.0.dist-info/WHEEL
yala-3.2.0.dist-info/entry_points.txt
yala-3.2.0.dist-info/top_level.txt
yala-3.2.0.dist-info/RECORD
