Metadata-Version: 2.1
Name: yala
Version: 3.2.0
Summary: Yet Another Linter Aggregator
Home-page: https://github.com/cemsbr/yala
Author: Carlos Eduardo Moreira dos Santos
Author-email: cems@cemshost.com.br
License: MIT
Keywords: linter check quality
Platform: UNKNOWN
Classifier: Development Status :: 5 - Production/Stable
Classifier: Intended Audience :: Developers
Classifier: Topic :: Software Development :: Build Tools
Classifier: Topic :: Software Development :: Quality Assurance
Classifier: Topic :: Software Development :: Testing
Classifier: License :: OSI Approved :: MIT License
Classifier: Programming Language :: Python :: 3
Classifier: Programming Language :: Python :: 3.6
Classifier: Programming Language :: Python :: 3.7
Classifier: Programming Language :: Python :: 3.8
Classifier: Programming Language :: Python :: 3.9
Classifier: Programming Language :: Python :: 3.10
License-File: LICENSE
Requires-Dist: docopt
Requires-Dist: isort (>=5)
Requires-Dist: pycodestyle
Requires-Dist: pylint
Provides-Extra: all
Requires-Dist: mypy ; extra == 'all'
Requires-Dist: pydocstyle ; extra == 'all'
Requires-Dist: pyflakes ; extra == 'all'
Requires-Dist: radon ; extra == 'all'
Provides-Extra: black
Requires-Dist: black ; extra == 'black'
Provides-Extra: dev
Requires-Dist: bandit ; extra == 'dev'
Requires-Dist: coverage ; extra == 'dev'
Requires-Dist: eradicate ; extra == 'dev'
Requires-Dist: rstcheck ; extra == 'dev'
Requires-Dist: safety ; extra == 'dev'
Requires-Dist: tox ; extra == 'dev'
Provides-Extra: flake8
Requires-Dist: flake8 ; extra == 'flake8'
Requires-Dist: flake8-polyfill ; extra == 'flake8'
Provides-Extra: mypy
Requires-Dist: mypy ; extra == 'mypy'
Provides-Extra: pydocstyle
Requires-Dist: pydocstyle ; extra == 'pydocstyle'
Provides-Extra: pyflakes
Requires-Dist: pyflakes ; extra == 'pyflakes'
Provides-Extra: pylint
Requires-Dist: pylint ; extra == 'pylint'
Provides-Extra: radon
Requires-Dist: radon ; extra == 'radon'
